predev_api/__init__.py
predev_api/client.py
predev_api/exceptions.py
predev_api-0.10.3.dist-info/licenses/LICENSE
predev_api-0.10.3.dist-info/METADATA
predev_api-0.10.3.dist-info/WHEEL
predev_api-0.10.3.dist-info/top_level.txt
predev_api-0.10.3.dist-info/RECORD
