Metadata-Version: 2.4
Name: predev-api
Version: 0.10.3
Summary: Python client for the Pre.dev Architect API - Generate comprehensive software specifications
Home-page: https://github.com/predotdev/predev-api
Author: Pre.dev
Author-email: support@pre.dev
License: MIT
Project-URL: Documentation, https://docs.pre.dev/
Project-URL: Bug Reports, https://github.com/predotdev/predev-api/issues
Project-URL: Source, https://github.com/predotdev/predev-api
Keywords: predev api specification architect ai
Classifier: Development Status :: 4 - Beta
Classifier: Intended Audience :: Developers
Classifier: Topic :: Software Development :: Libraries :: Python Modules
Classifier: License :: OSI Approved :: MIT License
Classifier: Programming Language :: Python :: 3
Classifier: Programming Language :: Python :: 3.8
Classifier: Programming Language :: Python :: 3.9
Classifier: Programming Language :: Python :: 3.10
Classifier: Programming Language :: Python :: 3.11
Classifier: Programming Language :: Python :: 3.12
Requires-Python: >=3.8
License-File: LICENSE
Requires-Dist: requests>=2.25.0
Dynamic: author
Dynamic: author-email
Dynamic: classifier
Dynamic: description
Dynamic: description-content-type
Dynamic: home-page
Dynamic: keywords
Dynamic: license
Dynamic: license-file
Dynamic: project-url
Dynamic: requires-dist
Dynamic: requires-python
Dynamic: summary
